mastsel/__init__.py
mastsel/_version.py
mastsel/ini_to_yaml.py
mastsel/mavisFormulas.py
mastsel/mavisLO.py
mastsel/mavisParams.py
mastsel/mavisParamsOld.py
mastsel/mavisPsf.py
mastsel/mavisUtilities.py
mastsel-1.3.11.dist-info/licenses/LICENSE
mastsel-1.3.11.dist-info/METADATA
mastsel-1.3.11.dist-info/WHEEL
mastsel-1.3.11.dist-info/top_level.txt
mastsel-1.3.11.dist-info/RECORD
