Metadata-Version: 2.4
Name: mastsel
Version: 1.3.11
Summary: Asterism Selection for MAVIS instrument
Author-email: Fabio Rossi <fabio.rossi@inaf.it>
License: MIT License
Project-URL: repository, https://github.com/astro-tiptop/MASTSEL
Requires-Python: >=3.9
License-File: LICENSE
Requires-Dist: astropy
Requires-Dist: matplotlib
Requires-Dist: numpy
Requires-Dist: PyYAML
Requires-Dist: scipy
Requires-Dist: symao>=1.0.2
Requires-Dist: astro-seeing>=1.2
Provides-Extra: gpu
Requires-Dist: cupy; extra == "gpu"
Dynamic: license-file
